korea_weather_api/__about__.py
korea_weather_api/__init__.py
korea_weather_api/base.py
korea_weather_api/forecasting.py
korea_weather_api/ground_observation.py
korea_weather_api/models.py
korea_weather_api/warning.py
korea_weather_api-0.2.1.dist-info/METADATA
korea_weather_api-0.2.1.dist-info/WHEEL
korea_weather_api-0.2.1.dist-info/licenses/LICENSE.txt
korea_weather_api-0.2.1.dist-info/RECORD
