Metadata-Version: 2.4
Name: korea-weather-api
Version: 0.2.1
Project-URL: Documentation, https://github.com/LEECHUNGGAK/korea-weather-api#readme
Project-URL: Issues, https://github.com/LEECHUNGGAK/korea-weather-api/issues
Project-URL: Source, https://github.com/LEECHUNGGAK/korea-weather-api
Author-email: Lee Chung Gak <lechga@yahoo.com>
License-Expression: MIT
License-File: LICENSE.txt
Classifier: Development Status :: 4 - Beta
Classifier: Programming Language :: Python
Classifier: Programming Language :: Python :: 3.11
Classifier: Programming Language :: Python :: Implementation :: CPython
Requires-Python: ~=3.11.0
Requires-Dist: requests~=2.32.0
